multi_level_sc_estimator/mlSC.py
multi_levelsc-0.1.2.dist-info/licenses/LICENSE
multi_levelsc-0.1.2.dist-info/METADATA
multi_levelsc-0.1.2.dist-info/WHEEL
multi_levelsc-0.1.2.dist-info/top_level.txt
multi_levelsc-0.1.2.dist-info/RECORD
