Metadata-Version: 2.4
Name: multi-levelSC
Version: 0.1.2
Summary: Package to implement the multi-level SC estimator
Author: null
License-Expression: Apache-2.0
Project-URL: Homepage, https://github.com/leabottmer/multi-level-sc-estimator
Project-URL: Changelog, https://github.com/leabottmer/multi-level-sc-estimator/releases
Project-URL: Issues, https://github.com/leabottmer/multi-level-sc-estimator/issues
Project-URL: CI, https://github.com/leabottmer/multi-level-sc-estimator/actions
Requires-Python: >=3.9
License-File: LICENSE
Requires-Dist: numpy
Requires-Dist: cvxpy
Requires-Dist: pandas
Requires-Dist: ray
Requires-Dist: scipy
Provides-Extra: test
Requires-Dist: pytest; extra == "test"
Dynamic: license-file
